LICENSE.txt
README.md
setup.cfg
setup.py
tradebot/__init__.py
tradebot.egg-info/PKG-INFO
tradebot.egg-info/SOURCES.txt
tradebot.egg-info/dependency_links.txt
tradebot.egg-info/requires.txt
tradebot.egg-info/top_level.txt
tradebot/backend/__init__.py
tradebot/backend/tradebot.py
tradebot/config/__init__.py
tradebot/config/tradebot_config.py
tradebot/stats/__init__.py
tradebot/stats/price_stats.py
tradebot/utils/__init__.py
tradebot/utils/exceptions.py
tradebot/utils/fileutils.py
tradebot/utils/utils.py