Metadata-Version: 2.1
Name: tradebot
Version: 0.0.7
Summary: A wrapper around the TDAmeritrade REST API
Home-page: https://github.com/abarolli/trade-bot
Download-URL: https://github.com/abarolli/trade-bot/archive/refs/tags/v0.0.7.tar.gz
Author: Adeiron Barolli
Author-email: obarolli@gmail.com
License: MIT
Keywords: stocks,statistics,rest api
Platform: UNKNOWN
Classifier: Development Status :: 3 - Alpha
Classifier: Intended Audience :: Developers
Classifier: Topic :: Software Development :: Build Tools
Classifier: License :: OSI Approved :: MIT License
Classifier: Programming Language :: Python :: 3.7
Classifier: Programming Language :: Python :: 3.8
Classifier: Programming Language :: Python :: 3.9
Classifier: Programming Language :: Python :: 3.10
License-File: LICENSE.txt
